neutron_lbaas/__init__.py
neutron_lbaas/_i18n.py
neutron_lbaas/agent_scheduler.py
neutron_lbaas/opts.py
neutron_lbaas/version.py
neutron_lbaas/agent/__init__.py
neutron_lbaas/agent/agent.py
neutron_lbaas/agent/agent_api.py
neutron_lbaas/agent/agent_device_driver.py
neutron_lbaas/agent/agent_manager.py
neutron_lbaas/cmd/__init__.py
neutron_lbaas/cmd/lbaasv2_agent.py
neutron_lbaas/common/__init__.py
neutron_lbaas/common/exceptions.py
neutron_lbaas/common/keystone.py
neutron_lbaas/common/cert_manager/__init__.py
neutron_lbaas/common/cert_manager/barbican_cert_manager.py
neutron_lbaas/common/cert_manager/cert_manager.py
neutron_lbaas/common/cert_manager/local_cert_manager.py
neutron_lbaas/common/cert_manager/barbican_auth/__init__.py
neutron_lbaas/common/cert_manager/barbican_auth/barbican_acl.py
neutron_lbaas/common/cert_manager/barbican_auth/common.py
neutron_lbaas/common/tls_utils/__init__.py
neutron_lbaas/common/tls_utils/cert_parser.py
neutron_lbaas/db/__init__.py
neutron_lbaas/db/loadbalancer/__init__.py
neutron_lbaas/db/loadbalancer/loadbalancer_dbv2.py
neutron_lbaas/db/loadbalancer/models.py
neutron_lbaas/db/migration/__init__.py
neutron_lbaas/db/migration/alembic_migrations/README
neutron_lbaas/db/migration/alembic_migrations/__init__.py
neutron_lbaas/db/migration/alembic_migrations/env.py
neutron_lbaas/db/migration/alembic_migrations/script.py.mako
neutron_lbaas/db/migration/alembic_migrations/versions/364f9b6064f0_agentv2.py
neutron_lbaas/db/migration/alembic_migrations/versions/4b6d8d5310b8_add_index_tenant_id.py
neutron_lbaas/db/migration/alembic_migrations/versions/4ba00375f715_edge_driver.py
neutron_lbaas/db/migration/alembic_migrations/versions/4deef6d81931_add_provisioning_and_operating_statuses.py
neutron_lbaas/db/migration/alembic_migrations/versions/CONTRACT_HEAD
neutron_lbaas/db/migration/alembic_migrations/versions/EXPAND_HEAD
neutron_lbaas/db/migration/alembic_migrations/versions/kilo_release.py
neutron_lbaas-14.0.1.dist-info/AUTHORS
neutron_lbaas-14.0.1.dist-info/LICENSE
neutron_lbaas-14.0.1.dist-info/METADATA
neutron_lbaas-14.0.1.dist-info/WHEEL
neutron_lbaas-14.0.1.dist-info/entry_points.txt
neutron_lbaas-14.0.1.dist-info/pbr.json
neutron_lbaas-14.0.1.dist-info/top_level.txt
neutron_lbaas-14.0.1.dist-info/RECORD
